release_tool.py
observability_testing_tool/config.schema.json
observability_testing_tool/main.py
observability_testing_tool/config/common.py
observability_testing_tool/config/executor.py
observability_testing_tool/config/parser.py
observability_testing_tool/obs/cloud_logging.py
observability_testing_tool/obs/cloud_monitoring.py
observability_testing_tool-1.1.0.dist-info/licenses/LICENSE
observability_testing_tool-1.1.0.dist-info/METADATA
observability_testing_tool-1.1.0.dist-info/WHEEL
observability_testing_tool-1.1.0.dist-info/entry_points.txt
observability_testing_tool-1.1.0.dist-info/top_level.txt
observability_testing_tool-1.1.0.dist-info/RECORD
