Metadata-Version: 2.4
Name: observability-testing-tool
Version: 1.1.0
Summary: 🛠️ A Python tool for generating bulk logs & metrics in Google Cloud. Simulate historical & live data to test alerts, refine LQL/SQL/PromQL queries, troubleshoot observability setups, and create structured data for training & automation.
Author-email: Federico Mestrone <federico@nekosoft.org>
License: GNU AFFERO GENERAL PUBLIC LICENSE
Project-URL: Homepage, https://github.com/fmestrone/observability-testing-tool
Requires-Python: >=3.12
License-File: LICENSE
Requires-Dist: google-cloud-logging==3.13.0
Requires-Dist: google-cloud-monitoring==2.28.0
Requires-Dist: pyyaml==6.0.3
Requires-Dist: jsonschema==4.26.0
Provides-Extra: build
Requires-Dist: twine; extra == "build"
Requires-Dist: build; extra == "build"
Dynamic: license-file
